odoo/addons/product_attachment_link/README.rst
odoo/addons/product_attachment_link/__init__.py
odoo/addons/product_attachment_link/__manifest__.py
odoo/addons/product_attachment_link/i18n/da_DK.po
odoo/addons/product_attachment_link/i18n/product_attachment_link.pot
odoo/addons/product_attachment_link/models/__init__.py
odoo/addons/product_attachment_link/models/product_product.py
odoo/addons/product_attachment_link/models/product_template.py
odoo/addons/product_attachment_link/readme/CONTRIBUTORS.rst
odoo/addons/product_attachment_link/readme/DESCRIPTION.rst
odoo/addons/product_attachment_link/static/description/icon.png
odoo/addons/product_attachment_link/static/description/index.html
odoo/addons/product_attachment_link/tests/__init__.py
odoo/addons/product_attachment_link/tests/test_product_attachment_link.py
odoo/addons/product_attachment_link/views/product_product_views.xml
odoo/addons/product_attachment_link/views/product_template_views.xml
odoo_addon_product_attachment_link-16.0.1.0.0.2.dist-info/METADATA
odoo_addon_product_attachment_link-16.0.1.0.0.2.dist-info/WHEEL
odoo_addon_product_attachment_link-16.0.1.0.0.2.dist-info/top_level.txt
odoo_addon_product_attachment_link-16.0.1.0.0.2.dist-info/RECORD
